nosedrive/__init__.py
nosedrive/main.py
nosedrive-0.0.7.dist-info/LICENSE
nosedrive-0.0.7.dist-info/METADATA
nosedrive-0.0.7.dist-info/WHEEL
nosedrive-0.0.7.dist-info/top_level.txt
nosedrive-0.0.7.dist-info/RECORD
