Metadata-Version: 2.1
Name: nosedrive
Version: 0.0.7
Summary: Simulate gamepad or mouse/keyboard inputs using Mediapipe tracking of Face joints.
Author-email: ASPHI Onlus <supporto@asphi.it>
Project-URL: Homepage, https://github.com/Fondazione-ASPHI/Nose-Drive
Project-URL: Issues, https://github.com/Fondazione-ASPHI/Nose-Drive/issues
Classifier: Programming Language :: Python :: 3
Classifier: License :: OSI Approved :: GNU General Public License v3 (GPLv3)
Classifier: Operating System :: OS Independent
Requires-Python: >=3.10
License-File: LICENSE
Requires-Dist: mediapipe >=0.8.11
Requires-Dist: numpy >=1.23.4
Requires-Dist: opencv-contrib-python >=4.6.0.66
Requires-Dist: Pillow >=9.2.0
Requires-Dist: pynput >=1.7.6
Requires-Dist: scipy >=1.12.0
Requires-Dist: vgamepad >=0.0.8
Requires-Dist: keyboard >=0.13.5
Requires-Dist: pywin32 >=306
Requires-Dist: pywin32-ctypes >=0.2.2
Requires-Dist: pyinstaller >=6.4.0
